ambra_sdk/__init__.py
ambra_sdk/addon/__init__.py
ambra_sdk/addon/addon.py
ambra_sdk/addon/dicom.py
ambra_sdk/addon/job.py
ambra_sdk/addon/study.py
ambra_sdk/api/__init__.py
ambra_sdk/api/api.py
ambra_sdk/api/async_api.py
ambra_sdk/api/base_api.py
ambra_sdk/async_addon/__init__.py
ambra_sdk/async_addon/addon.py
ambra_sdk/async_addon/dicom.py
ambra_sdk/async_addon/job.py
ambra_sdk/async_addon/study.py
ambra_sdk/async_context_manager.py
ambra_sdk/clear_params.py
ambra_sdk/deprecated.py
ambra_sdk/exceptions/__init__.py
ambra_sdk/exceptions/base.py
ambra_sdk/exceptions/service.py
ambra_sdk/exceptions/storage.py
ambra_sdk/models/__init__.py
ambra_sdk/models/base.py
ambra_sdk/models/fields.py
ambra_sdk/models/generated.py
ambra_sdk/models/models.py
ambra_sdk/pythonize.py
ambra_sdk/request_args.py
ambra_sdk/service/__init__.py
ambra_sdk/service/entrypoints/__init__.py
ambra_sdk/service/entrypoints/account.py
ambra_sdk/service/entrypoints/activity.py
ambra_sdk/service/entrypoints/analytics.py
ambra_sdk/service/entrypoints/annotation.py
ambra_sdk/service/entrypoints/anonymization.py
ambra_sdk/service/entrypoints/appointment.py
ambra_sdk/service/entrypoints/audit.py
ambra_sdk/service/entrypoints/case.py
ambra_sdk/service/entrypoints/customcode.py
ambra_sdk/service/entrypoints/customfield.py
ambra_sdk/service/entrypoints/destination.py
ambra_sdk/service/entrypoints/dicomdata.py
ambra_sdk/service/entrypoints/dictionary.py
ambra_sdk/service/entrypoints/filter.py
ambra_sdk/service/entrypoints/generated/account.py
ambra_sdk/service/entrypoints/generated/activity.py
ambra_sdk/service/entrypoints/generated/analytics.py
ambra_sdk/service/entrypoints/generated/annotation.py
ambra_sdk/service/entrypoints/generated/anonymization.py
ambra_sdk/service/entrypoints/generated/appointment.py
ambra_sdk/service/entrypoints/generated/audit.py
ambra_sdk/service/entrypoints/generated/case.py
ambra_sdk/service/entrypoints/generated/customcode.py
ambra_sdk-3.22.4.0.post1.dist-info/entry_points.txt
ambra_sdk-3.22.4.0.post1.dist-info/LICENSE
ambra_sdk-3.22.4.0.post1.dist-info/WHEEL
ambra_sdk-3.22.4.0.post1.dist-info/METADATA
ambra_sdk-3.22.4.0.post1.dist-info/RECORD
