Metadata-Version: 2.1
Name: ambra-sdk
Version: 3.22.4.0.post1
Summary: Ambrahealth python SDK
Home-page: https://github.com/dicomgrid/sdk-python
License: Apache-2.0
Keywords: ambrahealth,ambra
Author: Ambrahealth AI team
Author-email: python-sdk@ambrahealth.com
Maintainer: Alexander Kapustin
Maintainer-email: akapustin@ambrahealth.com
Requires-Python: >=3.6,<4.0
Classifier: License :: OSI Approved :: Apache Software License
Classifier: Programming Language :: Python :: 3
Classifier: Programming Language :: Python :: 3.10
Classifier: Programming Language :: Python :: 3.6
Classifier: Programming Language :: Python :: 3.7
Classifier: Programming Language :: Python :: 3.8
Classifier: Programming Language :: Python :: 3.9
Classifier: Topic :: Software Development :: Libraries
Classifier: Topic :: Software Development :: Libraries :: Python Modules
Requires-Dist: aiohttp (>=3.6.2,<4.0.0)
Requires-Dist: pydicom (>=2.0.0,<3.0.0)
Requires-Dist: python-box (>=5.1.1,<6.0.0)
Requires-Dist: requests (>=2.24.0,<3.0.0)
Project-URL: Documentation, https://dicomgrid.github.io/sdk-python/index.html
Project-URL: Repository, https://github.com/dicomgrid/sdk-python
